		{
		"obituario": [{	"id": 132,
				"titulo": "SR.",
				"nombre": "ALEJANDRO MANUEL",
				"apellido_paterno": "ÁLVAREZ",
				"apellido_materno": "SOLÍS",
				"fecha": "Lunes 16 de Abril",
				"mensaje_corto": "A LOS 32 AÑOS DE EDAD",
				"se_vela_en": "SE VELA EN CAPILLA DIAMANTE, MISIÓN FUNERAL RAÚL FLORES",
				"honras": "PENDIENTES",
				"descripcion": ""
			},
			{
				"id": 131,
				"titulo": "SR.",
				"nombre": "PEDRO",
				"apellido_paterno": "SALAS",
				"apellido_materno": "CORTEZ",
				"fecha": "Lunes 16 de Abril",
				"mensaje_corto": "A LOS 55 AÑOS DE EDAD",
				"se_vela_en": "SE VELA EN DOM. CON. EL CALABAZAL, DGO.",
				"honras": "PENDIENTES",
				"descripcion": ""
			},
			{
				"id": 130,
				"titulo": "SRA.",
				"nombre": "MARÍA CONCEPCIÓN",
				"apellido_paterno": "ZAMORA",
				"apellido_materno": "VARGAS",
				"fecha": "Domingo 15 de Abril",
				"mensaje_corto": "A LOS 83 AÑOS DE EDAD",
				"se_vela_en": "SE VELA EN C. PASEO DE LA PALMA S/N COL. ETA MPIO. RODEO, DGO.",
				"honras": "PENDIENTES",
				"descripcion": ""
			},
			{
				"id": 129,
				"titulo": "SR.",
				"nombre": "MIGUEL",
				"apellido_paterno": "PÉREZ",
				"apellido_materno": "RIVERA",
				"fecha": "Domingo 15 de Abril",
				"mensaje_corto": "A LOS 69 AÑOS DE EDAD",
				"se_vela_en": "SE VELA EN CAPILLA MISIÓN FUNERAL RAÚL FLORES DE TEPEHUANES, DGO.",
				"honras": "PENDIENTES",
				"descripcion": ""
			},
			{
				"id": 128,
				"titulo": "SR.",
				"nombre": "JESÚS ALFREDO",
				"apellido_paterno": "CHACON",
				"apellido_materno": "RODRIGUEZ",
				"fecha": "Domingo 15 de Abril",
				"mensaje_corto": "A LOS 34 AÑOS DE EDAD",
				"se_vela_en": "SE VELA EN CAPILLA DIAMANTE DE MISIÓN FUNERAL RAÚL FLORES",
				"honras": "PENDIENTES",
				"descripcion": ""
			},
			{
				"id": 127,
				"titulo": "SRA.",
				"nombre": "MARÍA DEL ROSARIO",
				"apellido_paterno": "LOZANO",
				"apellido_materno": "GARCÍA",
				"fecha": "Domingo 15 de Abril",
				"mensaje_corto": "A LOS 84 AÑOS DE EDAD",
				"se_vela_en": "SE VELA EN DOM. CON LA OCHOA, POANAS, DGO.",
				"honras": "A LAS 12:00 HRS. EN EL TEMPLO SAN MIGUEL, SE DESPIDE EN EL PANTEÓN DEL LUGAR",
				"descripcion": ""
			},
			{
				"id": 126,
				"titulo": "SR.",
				"nombre": "ALEJANDRO",
				"apellido_paterno": "HERNÁNDEZ",
				"apellido_materno": "KUHN",
				"fecha": "Sábado 14 de Abril",
				"mensaje_corto": "A LOS 69 AÑOS DE EDAD",
				"se_vela_en": "SE VELA EN CAPILLA ORO Y PLATA DE MISIÓN FUNERAL RAÚL FLORES",
				"honras": "A LAS 18:00 HRS. SERVICIO BIBLICO EN LA MISMA CAPILLA, SE DESPIDE PARA SU CREMACIÓN",
				"descripcion": ""
			},
			{
				"id": 125,
				"titulo": "SR.",
				"nombre": "GENARO",
				"apellido_paterno": "ÁVILA",
				"apellido_materno": "IBARRA",
				"fecha": "Sábado 14 de Abril",
				"mensaje_corto": "A LOS 68 AÑOS DE EDAD",
				"se_vela_en": "SE VELA EN CAPILLA ORO DE MISIÓN FUNERAL RAÚL FLORES",
				"honras": "A LAS 9:00 HRS. EN EL TEMPLO DE SAN JOSÉ OBRERO (INFONAVIT), SE DESPIDE PARA SU CREMACIÓN",
				"descripcion": ""
			},
			{
				"id": 124,
				"titulo": "SR.",
				"nombre": "RAMIRO",
				"apellido_paterno": "PÉREZ",
				"apellido_materno": "FLORES",
				"fecha": "Sábado 14 de Abril",
				"mensaje_corto": "A LOS 80 AÑOS DE EDAD",
				"se_vela_en": "SE VELA EN EJIDO LA GLORIETA, GÓMEZ PALACIO, DGO.",
				"honras": "PENDIENTES",
				"descripcion": ""
			},
			{
				"id": 123,
				"titulo": "SR.",
				"nombre": "MANUEL",
				"apellido_paterno": "ÁVALOS",
				"apellido_materno": "REYES",
				"fecha": "Viernes 13 de Abril",
				"mensaje_corto": "A LOS 83 AÑOS DE EDAD",
				"se_vela_en": "SE VELA EN CAPILLA DIAMANTE DE MISIÓN FUNERAL RAÚL FLORES",
				"honras": "A LAS 11:00 HRS. EN EL TEMPLO DE SAN AGUSTÍN, SE DESPIDE EN EL PANTEÓN JARDÍN",
				"descripcion": ""
			},
			{
				"id": 123,
				"titulo": "SRA.",
				"nombre": "REBECA",
				"apellido_paterno": "SÁNCHEZ",
				"apellido_materno": "SÁNCHEZ",
				"fecha": "Viernes 13 de Abril",
				"mensaje_corto": "A LOS 47 AÑOS DE EDAD",
				"se_vela_en": "SE VELA EN CAPILLA ESMERALDA DE MISIÓN FUNERAL RAÚL FLORES",
				"honras": "A LAS 16:00 HRS. SERVICIO BIBLICO EN LA MISMA CAPILLA, SE DESPIDE EN EL PANTEÓN DE ORIENTE",
				"descripcion": ""
			}
		],
		"obituario_ingles": [{	"id": 132,
				"titulo": "SR.",
				"nombre": "ALEJANDRO MANUEL",
				"apellido_paterno": "ÁLVAREZ",
				"apellido_materno": "SOLÍS",
				"fecha": "Monday, April 16",
				"mensaje_corto": "AT THE AGE OF 32 YEARS",
				"se_vela_en": "SE VELA EN CAPILLA DIAMANTE, MISIÓN FUNERAL RAÚL FLORES",
				"honras": "PENDIENTES",
				"descripcion": ""
			},
			{
				"id": 131,
				"titulo": "SR.",
				"nombre": "PEDRO",
				"apellido_paterno": "SALAS",
				"apellido_materno": "CORTEZ",
				"fecha": "Monday, April 16",
				"mensaje_corto": "AT THE AGE OF 55 YEARS",
				"se_vela_en": "SE VELA EN DOM. CON. EL CALABAZAL, DGO.",
				"honras": "PENDIENTES",
				"descripcion": ""
			},
			{
				"id": 130,
				"titulo": "SRA.",
				"nombre": "MARÍA CONCEPCIÓN",
				"apellido_paterno": "ZAMORA",
				"apellido_materno": "VARGAS",
				"fecha": "Sunday, April 15",
				"mensaje_corto": "AT THE AGE OF 83 YEARS",
				"se_vela_en": "SE VELA EN C. PASEO DE LA PALMA S/N COL. ETA MPIO. RODEO, DGO.",
				"honras": "PENDIENTES",
				"descripcion": ""
			},
			{
				"id": 129,
				"titulo": "SR.",
				"nombre": "MIGUEL",
				"apellido_paterno": "PÉREZ",
				"apellido_materno": "RIVERA",
				"fecha": "Sunday, April 15",
				"mensaje_corto": "AT THE AGE OF 69 YEARS",
				"se_vela_en": "SE VELA EN CAPILLA FUNERALES RAÚL FLORES EN TEPEHUANES, DGO.",
				"honras": "PENDIENTES",
				"descripcion": ""
			},
			{
				"id": 128,
				"titulo": "SR.",
				"nombre": "JESÚS ALFREDO",
				"apellido_paterno": "CHACON",
				"apellido_materno": "RODRIGUEZ",
				"fecha": "Sunday, April 15",
				"mensaje_corto": "AT THE AGE OF 34 YEARS",
				"se_vela_en": "SE VELA EN CAPILLA DIAMANTE DE MISIÓN FUNERAL RAÚL FLORES",
				"honras": "PENDIENTES",
				"descripcion": ""
			},
			{
				"id": 127,
				"titulo": "SRA.",
				"nombre": "MARÍA DEL ROSARIO",
				"apellido_paterno": "LOZANO",
				"apellido_materno": "GARCÍA",
				"fecha": "Sunday, April 15",
				"mensaje_corto": "AT THE AGE OF 84 YEARS",
				"se_vela_en": "SE VELA EN DOM. CON LA OCHOA, RODEO DGO",
				"honras": "A LAS 12:00 HRS. EN EL TEMPLO SAN MIGUEL, SE DESPIDE EN EL PANTEÓN DEL LUGAR",
				"descripcion": ""
			},
			{
				"id": 126,
				"titulo": "SR.",
				"nombre": "ALEJANDRO",
				"apellido_paterno": "HERNÁNDEZ",
				"apellido_materno": "KUHN",
				"fecha": "Saturday, April 14",
				"mensaje_corto": "AT THE AGE OF 69 YEARS",
				"se_vela_en": "SE VELA EN CAPILLA ORO Y PLATA DE MISIÓN FUNERAL RAÚL FLORES",
				"honras": "A LAS 18:00 HRS. SERVICIO BIBLICO EN LA MISMA CAPILLA, SE DESPIDE PARA SU CREMACIÓN",
				"descripcion": ""
			},
			{
				"id": 125,
				"titulo": "SR.",
				"nombre": "GENARO",
				"apellido_paterno": "ÁVILA",
				"apellido_materno": "IBARRA",
				"fecha": "Saturday, April 14",
				"mensaje_corto": "AT THE AGE OF 68 YEARS",
				"se_vela_en": "SE VELA EN CAPILLA ORO DE MISIÓN FUNERAL RAÚL FLORES",
				"honras": "A LAS 9:00 HRS. EN EL TEMPLO DE SAN JOSÉ OBRERO (INFONAVIT), SE DESPIDE PARA SU CREMACIÓN",
				"descripcion": ""
			},
			{
				"id": 124,
				"titulo": "SR.",
				"nombre": "RAMIRO",
				"apellido_paterno": "PÉREZ",
				"apellido_materno": "FLORES",
				"fecha": "Saturday, April 14",
				"mensaje_corto": "AT THE AGE OF 80 YEARS",
				"se_vela_en": "SE VELA EN EJIDO LA GLORIETA, GÓMEZ PALACIO, DGO.",
				"honras": "PENDIENTES",
				"descripcion": ""
			},
			{
				"id": 123,
				"titulo": "SR.",
				"nombre": "MANUEL",
				"apellido_paterno": "ÁVALOS",
				"apellido_materno": "REYES",
				"fecha": "Friday, April 13",
				"mensaje_corto": "AT THE AGE OF 83 YEARS",
				"se_vela_en": "SE VELA EN CAPILLA DIAMANTE DE MISIÓN FUNERAL RAÚL FLORES",
				"honras": "A LAS 11:00 HRS. EN EL TEMPLO DE SAN AGUSTÍN, SE DESPIDE EN EL PANTEÓN JARDÍN",
				"descripcion": ""
			},
			{
				"id": 123,
				"titulo": "SRA.",
				"nombre": "REBECA",
				"apellido_paterno": "SÁNCHEZ",
				"apellido_materno": "SÁNCHEZ",
				"fecha": "Friday, April 13",
				"mensaje_corto": "AT THE AGE OF 47 YEARS",
				"se_vela_en": "SE VELA EN CAPILLA ESMERALDA DE MISIÓN FUNERAL RAÚL FLORES",
				"honras": "A LAS 16:00 HRS. SERVICIO BIBLICO EN LA MISMA CAPILLA, SE DESPIDE EN EL PANTEÓN DE ORIENTE",
				"descripcion": ""
			}
		]
	}
