{
  "obituario": [
    {
      "id": 229,
      "titulo": "",
      "nombre": "Everarda Maria",
      "apellido_paterno": "Sanabria",
      "apellido_materno": "Esquivel",
      "fecha": "Martes 21 de Enero",
      "mensaje_corto": "A la edad de 92 años",
      "se_vela_en": "Suc. Dolores del Río en Capilla Diamante",
      "honras": "Pendientes",
      "descripcion": ""
    },
    {
      "id": 228,
      "titulo": "",
      "nombre": "Margarita",
      "apellido_paterno": "Sanchez",
      "apellido_materno": "Barron",
      "fecha": "Martes 21 de Enero",
      "mensaje_corto": "A la edad de 70 años",
      "se_vela_en": "Calle Costa Rica #515 Col. Fco. Zarco",
      "honras": "15:00hrs Templo San Francisco de Asis y se despide en panteón de Oriente",
      "descripcion": ""
    },
    {
      "id": 227,
      "titulo": "",
      "nombre": "Norma Leticia",
      "apellido_paterno": "Cordero",
      "apellido_materno": "Flores",
      "fecha": "Martes 21 de Enero",
      "mensaje_corto": "A la edad de 58 años",
      "se_vela_en": "Suc. Dolores del Río en Capilla Esmeralda",
      "honras": "Honras 11:00hrs Templo de Ntra. Sra. de Fátima y del Carmen y se depise en panteón de Oriente",
      "descripcion": ""
    },
    {
      "id": 226,
      "titulo": "",
      "nombre": "Bertha ",
      "apellido_paterno": "Contreras",
      "apellido_materno": "Rodriguez",
      "fecha": "Martes 21 de Enero",
      "mensaje_corto": "A la edad de 86 años",
      "se_vela_en": "Suc. Dolores del Río en Capilla Diamante",
      "honras": "20 de Enero, misa en capilla Diamante y se despidió para su cremación",
      "descripcion": ""
    }
  ],
  "obituario_ingles": [
    {
      "id": 229,
      "titulo": "",
      "nombre": "Everarda Maria",
      "apellido_paterno": "Sanabria",
      "apellido_materno": "Esquivel",
      "fecha": "Tuesday, Junuary 21",
      "mensaje_corto": "At the age of 92 years",
      "se_vela_en": "Suc. Dolores del Río en Capilla Diamante",
      "honras": "Pendents",
      "descripcion": ""
    },
    {
      "id": 228,
      "titulo": "",
      "nombre": "Margarita",
      "apellido_paterno": "Sanchez",
      "apellido_materno": "Barron",
      "fecha": "Tuesday, Junuary 21",
      "mensaje_corto": "At the age of 70 years",
      "se_vela_en": "Calle Costa Rica #515 Col. Fco. Zarco",
      "honras": "15:00hrs Templo San Francisco de Asis y se despide en panteón de Oriente",
      "descripcion": ""
    },
    {
      "id": 227,
      "titulo": "",
      "nombre": "Norma Leticia",
      "apellido_paterno": "Cordero",
      "apellido_materno": "Flores",
      "fecha": "Tuesday, Junuary 21",
      "mensaje_corto": "At the age of 58 years",
      "se_vela_en": "Suc. Dolores del Río en Capilla Esmeralda",
      "honras": "Honras 11:00hrs Templo de Ntra. Sra. de Fátima y del Carmen y se depise en panteón de Oriente",
      "descripcion": ""
    },
    {
      "id": 226,
      "titulo": "",
      "nombre": "Bertha ",
      "apellido_paterno": "Contreras",
      "apellido_materno": "Rodriguez",
      "fecha": "Martes 21 de Enero",
      "mensaje_corto": "A la edad de 86 años",
      "se_vela_en": "Suc. Dolores del Río en Capilla Diamante",
      "honras": "20 de Enero, misa en capilla Diamante y se despidió para su cremación",
      "descripcion": ""
    }
  ]
}
