		{
			"obituario": [
				{
					"id": 420,
					"titulo": "",
					"nombre": "ROMAN",
					"apellido_paterno": "JAQUEZ",
					"apellido_materno": "",
					"fecha": "LUNES 17 DE SEPTIEMBRE",
					"mensaje_corto": "A LA EDAD DE 71 AÑOS",
					"se_vela_en": "SE VELA EN GARAME DE ABAJO, SANTIAGO PAPASQUIARO, DGO.",
					"honras": "HONRAS PENDIENTES.",
					"descripcion": ""
				},
				{
					"id": 419,
					"titulo": "",
					"nombre": "JESUS",
					"apellido_paterno": "NUÑEZ",
					"apellido_materno": "DUARTE",
					"fecha": "LUNES 17 DE SEPTIEMBRE",
					"mensaje_corto": "A LA EDAD DE 90 AÑOS",
					"se_vela_en": "SE VELA EN GARAME DE ARRIBA, SANTIAGO PAPASQUIARO, DGO.",
					"honras": "HONRAS PENDIENTES.",
					"descripcion": ""
				},
				{
					"id": 418,
					"titulo": "",
					"nombre": "JOSE DEL PILAR",
					"apellido_paterno": "LAZCANO",
					"apellido_materno": "LARES",
					"fecha": "LUNES 17 DE SEPTIEMBRE",
					"mensaje_corto": "A LA EDAD DE 40 AÑOS",
					"se_vela_en": "SE VELA DOM. CON. TEPEHUANES, DGO.",
					"honras": "HONRAS 16:00 HRS.TEMPLO SANTA CATARINA.SE DESPIDE EN PANTEÓN DEL LUGAR.",
					"descripcion": ""
				},
				{
					"id": 417,
					"titulo": "",
					"nombre": "MAGDALENO",
					"apellido_paterno": "MARTINEZ",
					"apellido_materno": "SALCIDO",
					"fecha": "SABADO 15 DE SEPTIEMBRE",
					"mensaje_corto": "A LA EDAD DE 74 AÑOS",
					"se_vela_en": "SE VELA EN DOMICILIO CONOCIDO J. REFUGIO SALCIDO",
					"honras": "HONRAS PENDIENTES",
					"descripcion": ""
				},
				{
					"id": 416,
					"titulo": "",
					"nombre": "MA TOMASA",
					"apellido_paterno": "ZURITA",
					"apellido_materno": "MEJORADO",
					"fecha": "SABADO 15 DE SEPTIEMBRE",
					"mensaje_corto": "A LA EDAD DE 63 AÑOS",
					"se_vela_en": "SE VELA EN SANTIAGO PAPASQUIARO",
					"honras": "HONRAS 16:00 TEMPLO CRISTO REY",
					"descripcion": ""
				},
				{
					"id": 415,
					"titulo": "",
					"nombre": "EVANGELINA",
					"apellido_paterno": "FAVELA",
					"apellido_materno": "REYES",
					"fecha": "SABADO 15 DE SEPTIEMBRE",
					"mensaje_corto": "A LA EDAD DE 63 AÑOS",
					"se_vela_en": "SE VELA DOM. CON. LABOR DE GUADALUPE, DGO.",
					"honras": "SALIDA DIRECTA AL PANTEÓN DEL LUGAR 16:00",
					"descripcion": ""
				},
				{
					"id": 414,
					"titulo": "",
					"nombre": "ARCADIO",
					"apellido_paterno": "FLORES",
					"apellido_materno": "ESPINOZA",
					"fecha": "JUEVES 13 DE SEPTIEMBRE",
					"mensaje_corto": "A LA EDAD DE 82 AÑOS",
					"se_vela_en": "SE VELA DOM.CON.MORCILLO,DGO.",
					"honras": "HONRAS 14:00 HRS.TEMPLO NTRA. SRA. DEL REFUGIO.SE DESPIDE EN PANTEÓN DEL LUGAR.",
					"descripcion": ""
				},
				{
					"id": 413,
					"titulo": "",
					"nombre": "MARIA GUADALUPE",
					"apellido_paterno": "DIAZ",
					"apellido_materno": "CHAVEZ",
					"fecha": "JUEVES 13 DE SEPTIEMBRE",
					"mensaje_corto": "A LA EDAD DE 84 AÑOS",
					"se_vela_en": "SE VELA ENCINO DE LA PAZ VILLA OCAMPO,DGO.",
					"honras": "HONRAS 10:00 HRS.TEMPLO NTRA. SRA. DE LA PAZ.SE DESPIDE EN PANTEÓN DEL LUGAR.",
					"descripcion": ""
				}
				
			],
			"obituario_ingles": [
				{
					"id": 420,
					"titulo": "",
					"nombre": "ROMAN",
					"apellido_paterno": "JAQUEZ",
					"apellido_materno": "       ",
					"fecha": "MONDAY SEPTEMBER 17",
					"mensaje_corto": "A LA EDAD DE 71 AÑOS",
					"se_vela_en": "SE VELA EN GARAME DE ABAJO, SANTIAGO PAPASQUIARO, DGO.",
					"honras": "HONRAS PENDIENTES.",
					"descripcion": ""
				},
				{
					"id": 419,
					"titulo": "",
					"nombre": "JESUS",
					"apellido_paterno": "NUÑEZ",
					"apellido_materno": "DUARTE",
					"fecha": "MONDAY SEPTEMBER 17",
					"mensaje_corto": "A LA EDAD DE 90 AÑOS",
					"se_vela_en": "SE VELA EN GARAME DE ARRIBA, SANTIAGO PAPASQUIARO, DGO.",
					"honras": "HONRAS PENDIENTES.",
					"descripcion": ""
				},
				{
					"id": 418,
					"titulo": "",
					"nombre": "JOSE DEL PILAR",
					"apellido_paterno": "LAZCANO",
					"apellido_materno": "LARES",
					"fecha": "MONDAY SEPTEMBER 17",
					"mensaje_corto": "A LA EDAD DE 40 AÑOS",
					"se_vela_en": "SE VELA DOM. CON. TEPEHUANES, DGO.",
					"honras": "HONRAS 16:00 HRS.TEMPLO SANTA CATARINA.SE DESPIDE EN PANTEÓN DEL LUGAR.",
					"descripcion": ""
				},
				{
					"id": 417,
					"titulo": "",
					"nombre": "MAGDALENO",
					"apellido_paterno": "MARTINEZ",
					"apellido_materno": "SALCIDO",
					"fecha": "SATURDAY SEPTEMBER 15",
					"mensaje_corto": "A LA EDAD DE 74 AÑOS",
					"se_vela_en": "SE VELA EN DOMICILIO CONOCIDO J. REFUGIO SALCIDO",
					"honras": "HONRAS PENDIENTES",
					"descripcion": ""
				},
				{
					"id": 416,
					"titulo": "",
					"nombre": "MA TOMASA",
					"apellido_paterno": "ZURITA",
					"apellido_materno": "MEJORADO",
					"fecha": "SATURDAY SEPTEMBER 15",
					"mensaje_corto": "A LA EDAD DE 63 AÑOS",
					"se_vela_en": "SE VELA EN SANTIAGO PAPASQUIARO",
					"honras": "HONRAS 16:00 TEMPLO CRISTO REY",
					"descripcion": ""
				},
				{
					"id": 415,
					"titulo": "",
					"nombre": "EVANGELINA",
					"apellido_paterno": "FAVELA",
					"apellido_materno": "REYES",
					"fecha": "SATURDAY SEPTEMBER 15",
					"mensaje_corto": "A LA EDAD DE 63 AÑOS",
					"se_vela_en": "SE VELA DOM. CON. LABOR DE GUADALUPE, DGO.",
					"honras": "SALIDA DIRECTA AL PANTEÓN DEL LUGAR 16:00",
					"descripcion": ""
				},
				{
					"id": 414,
					"titulo": "",
					"nombre": "ARCADIO",
					"apellido_paterno": "FLORES",
					"apellido_materno": "ESPINOZA",
					"fecha": "THURSDAY SEPTEMBER 13",
					"mensaje_corto": "A LA EDAD DE 82 AÑOS",
					"se_vela_en": "SE VELA DOM.CON.MORCILLO,DGO.",
					"honras": "HONRAS 14:00 HRS.TEMPLO NTRA. SRA. DEL REFUGIO.SE DESPIDE EN PANTEÓN DEL LUGAR.",
					"descripcion": ""
				},
				{
					"id": 413,
					"titulo": "",
					"nombre": "MARIA GUADALUPE",
					"apellido_paterno": "DIAZ",
					"apellido_materno": "CHAVEZ",
					"fecha": "THURSDAY SEPTEMBER 13",
					"mensaje_corto": "A LA EDAD DE 84 AÑOS",
					"se_vela_en": "SE VELA ENCINO DE LA PAZ VILLA OCAMPO,DGO.",
					"honras": "HONRAS 10:00 HRS.TEMPLO NTRA. SRA. DE LA PAZ.SE DESPIDE EN PANTEÓN DEL LUGAR.",
					"descripcion": ""
				}
				
			]
		}
